odoo/addons/account_bank_statement_import_paypal/README.rst
odoo/addons/account_bank_statement_import_paypal/__init__.py
odoo/addons/account_bank_statement_import_paypal/__manifest__.py
odoo/addons/account_bank_statement_import_paypal/data/maps.xml
odoo/addons/account_bank_statement_import_paypal/i18n/account_bank_statement_import_paypal.pot
odoo/addons/account_bank_statement_import_paypal/i18n/es.po
odoo/addons/account_bank_statement_import_paypal/migrations/11.0.3.0.0/post-migration.py
odoo/addons/account_bank_statement_import_paypal/models/__init__.py
odoo/addons/account_bank_statement_import_paypal/models/account_bank_statement_import.py
odoo/addons/account_bank_statement_import_paypal/models/account_bank_statement_import_paypal_mapping.py
odoo/addons/account_bank_statement_import_paypal/models/account_bank_statement_import_paypal_parser.py
odoo/addons/account_bank_statement_import_paypal/readme/CONFIGURE.rst
odoo/addons/account_bank_statement_import_paypal/readme/CONTRIBUTORS.rst
odoo/addons/account_bank_statement_import_paypal/readme/DESCRIPTION.rst
odoo/addons/account_bank_statement_import_paypal/readme/HISTORY.rst
odoo/addons/account_bank_statement_import_paypal/readme/USAGE.rst
odoo/addons/account_bank_statement_import_paypal/security/ir.model.access.csv
odoo/addons/account_bank_statement_import_paypal/static/description/icon.png
odoo/addons/account_bank_statement_import_paypal/static/description/index.html
odoo/addons/account_bank_statement_import_paypal/tests/__init__.py
odoo/addons/account_bank_statement_import_paypal/tests/test_account_bank_statement_import_paypal.py
odoo/addons/account_bank_statement_import_paypal/tests/fixtures/activity_en.csv
odoo/addons/account_bank_statement_import_paypal/tests/fixtures/empty_activity.csv
odoo/addons/account_bank_statement_import_paypal/tests/fixtures/statement_en.csv
odoo/addons/account_bank_statement_import_paypal/tests/fixtures/statement_es.csv
odoo11_addon_account_bank_statement_import_paypal-11.0.3.0.1.dist-info/METADATA
odoo11_addon_account_bank_statement_import_paypal-11.0.3.0.1.dist-info/WHEEL
odoo11_addon_account_bank_statement_import_paypal-11.0.3.0.1.dist-info/top_level.txt
odoo11_addon_account_bank_statement_import_paypal-11.0.3.0.1.dist-info/RECORD
