Metadata-Version: 2.1
Name: odoo11-addon-account-bank-statement-import-paypal
Version: 11.0.3.0.1
Summary: Import PayPal CSV files as Bank Statements in Odoo
Home-page: https://github.com/OCA/bank-statement-import
Author: Akretion, Brainbean Apps, Odoo Community Association (OCA)
Author-email: support@odoo-community.org
License: AGPL-3
Platform: UNKNOWN
Classifier: Programming Language :: Python
Classifier: Framework :: Odoo
Classifier: License :: OSI Approved :: GNU Affero General Public License v3
Requires-Python: >=2.7, !=3.0.*, !=3.1.*, !=3.2.*, !=3.3.*, !=3.4.*
Requires-Dist: odoo11-addon-multi-step-wizard
Requires-Dist: odoo11-addon-web-widget-dropdown-dynamic
Requires-Dist: odoo (<11.1dev,>=11.0a)
